kelpmark/__init__.py
kelpmark/__main__.py
kelpmark/mainwindow.ui
kelpmark-1.0.1.dist-info/METADATA
kelpmark-1.0.1.dist-info/WHEEL
kelpmark-1.0.1.dist-info/entry_points.txt
kelpmark-1.0.1.dist-info/RECORD
