Metadata-Version: 2.1
Name: KelpMark
Version: 1.0.1
Summary: Watermark images or PDF
Project-URL: Project, https://gitlab.com/hydrargyrum/kelpmark
Author-email: Hg <dev@indigo.re>
License-Expression: Unlicense
Keywords: document,image,kyc,pdf,watermark
Classifier: Development Status :: 4 - Beta
Classifier: License :: Public Domain
Classifier: Programming Language :: Python :: 3
Classifier: Programming Language :: Python :: 3.5
Classifier: Programming Language :: Python :: 3.6
Classifier: Programming Language :: Python :: 3.7
Classifier: Programming Language :: Python :: 3.8
Classifier: Programming Language :: Python :: 3.9
Classifier: Programming Language :: Python :: 3.10
Classifier: Topic :: Desktop Environment
Classifier: Topic :: Multimedia :: Graphics
Classifier: Topic :: Software Development :: Libraries :: Python Modules
Classifier: Topic :: Utilities
Requires-Dist: pyqt5
Requires-Dist: python-poppler-qt5
